LICENSE
MANIFEST.in
README.md
setup.py
ConGL/__init__.py
ConGL.egg-info/PKG-INFO
ConGL.egg-info/SOURCES.txt
ConGL.egg-info/dependency_links.txt
ConGL.egg-info/top_level.txt
ConGL/bin/congl.cp310-win32.pyd
ConGL/bin/congl.cp310-win_amd64.pyd
ConGL/bin/congl.cp36-win32.pyd
ConGL/bin/congl.cp36-win_amd64.pyd
ConGL/bin/congl.cp37-win32.pyd
ConGL/bin/congl.cp37-win_amd64.pyd
ConGL/bin/congl.cp38-win32.pyd
ConGL/bin/congl.cp38-win_amd64.pyd
ConGL/bin/congl.cp39-win32.pyd
ConGL/bin/congl.cp39-win_amd64.pyd
ConGL/docs/colors.py
ConGL/docs/congl.py
ConGL/docs/eng2D.py
ConGL/docs/keys.py
ConGL/docs/shapes.py
ConGL/docs/texture.py