Metadata-Version: 2.1
Name: ConGL
Version: 0.2.2
Summary: Console Graphics Library
Home-page: https://github.com/bulbaME/ConGL/tree/master/PY_MODULE
Author: bulba
Author-email: rily.ylir1@gmail.com
License: MIT
Keywords: console,cmd,engine,congl,terminal
Platform: win
Classifier: Intended Audience :: Developers
Classifier: License :: OSI Approved :: MIT License
Classifier: Programming Language :: Python :: 3
Classifier: Programming Language :: Python :: 3.6
Classifier: Programming Language :: Python :: 3.7
Classifier: Programming Language :: Python :: 3.8
Classifier: Programming Language :: Python :: 3.9
Classifier: Programming Language :: Python :: 3.10
License-File: LICENSE
